voxos/__init__.py
voxos/version.py
voxos/services/__init__.py
voxos/services/agents.py
voxos/services/transcription.py
voxos/ui/__init__.py
voxos/ui/context_menu.py
voxos/ui/hud.py
voxos/ui/system_tray.py
voxos/ui/text_editor.py
voxos/utils/__init__.py
voxos/utils/audio_recorder.py
voxos/utils/common.py
voxos/utils/constants.py
voxos/utils/cursor.py
voxos/utils/hotkeys.py
voxos/utils/prompts.py
voxos/utils/runner.py
voxos/utils/volume/__init__.py
voxos/utils/volume/darwin.py
voxos/utils/volume/linux.py
voxos/utils/volume/windows.py
voxos-0.0.1.dist-info/COPYING
voxos-0.0.1.dist-info/LICENSE
voxos-0.0.1.dist-info/METADATA
voxos-0.0.1.dist-info/WHEEL
voxos-0.0.1.dist-info/top_level.txt
voxos-0.0.1.dist-info/RECORD
