Metadata-Version: 2.1
Name: voxos
Version: 0.0.1
Summary: UNKNOWN
License: UNKNOWN
Platform: UNKNOWN
License-File: LICENSE
License-File: COPYING
Requires-Dist: aiohttp <4.0,>=3.9
Requires-Dist: aiosignal <2.0,>=1.3
Requires-Dist: async-timeout <5.0,>=4.0
Requires-Dist: attrs <24.0,>=23.1
Requires-Dist: certifi <2024.0,>=2023.11
Requires-Dist: charset-normalizer <4.0,>=3.3
Requires-Dist: colorama <1.0,>=0.4
Requires-Dist: frozenlist <2.0,>=1.4
Requires-Dist: idna <4.0,>=3.6
Requires-Dist: keyboard <1.0,>=0.13
Requires-Dist: multidict <7.0,>=6.0
Requires-Dist: numpy <2.0,>=1.0
Requires-Dist: openai <2.0,>=1.0
Requires-Dist: pillow
Requires-Dist: pyautogui
Requires-Dist: PyAudio <1.0,>=0.2
Requires-Dist: PyQt5 <6.0,>=5.15
Requires-Dist: PyQt5-Qt5 <6.0,>=5.15
Requires-Dist: PyQt5-sip <13.0,>=12.13
Requires-Dist: regex <2024.0,>=2023.12
Requires-Dist: requests <3.0,>=2.31
Requires-Dist: tiktoken <1.0,>=0.5
Requires-Dist: tqdm <5.0,>=4.66
Requires-Dist: urllib3 <3.0,>=2.1
Requires-Dist: yarl <2.0,>=1.9
Requires-Dist: osascript ; sys_platform == "darwin"
Requires-Dist: pyalsaaudio ; sys_platform == "linux"
Requires-Dist: pycaw >=20230407 ; sys_platform == "win32"
